homematicip/EventHook.py
homematicip/__init__.py
homematicip/__main__.py
homematicip/_version.py
homematicip/access_point_update_state.py
homematicip/async_home.py
homematicip/auth.py
homematicip/class_maps.py
homematicip/client.py
homematicip/device.py
homematicip/functionalHomes.py
homematicip/group.py
homematicip/home.py
homematicip/location.py
homematicip/oauth_otk.py
homematicip/rule.py
homematicip/securityEvent.py
homematicip/weather.py
homematicip/base/__init__.py
homematicip/base/channel_event.py
homematicip/base/constants.py
homematicip/base/enums.py
homematicip/base/functionalChannels.py
homematicip/base/helpers.py
homematicip/base/homematicip_object.py
homematicip/cli/hmip_batch.py
homematicip/cli/hmip_cli.py
homematicip/cli/hmip_generate_auth_token.py
homematicip/commands/__init__.py
homematicip/commands/functional_channel_commands.py
homematicip/connection/__init__.py
homematicip/connection/buckets.py
homematicip/connection/client_characteristics_builder.py
homematicip/connection/client_token_builder.py
homematicip/connection/connection_context.py
homematicip/connection/connection_factory.py
homematicip/connection/connection_url_resolver.py
homematicip/connection/rate_limited_rest_connection.py
homematicip/connection/rest_connection.py
homematicip/connection/websocket_handler.py
homematicip/exceptions/__init__.py
homematicip/exceptions/connection_exceptions.py
homematicip/exceptions/home_exceptions.py
homematicip-2.4.0.dist-info/licenses/LICENSE.txt
homematicip-2.4.0.dist-info/METADATA
homematicip-2.4.0.dist-info/WHEEL
homematicip-2.4.0.dist-info/entry_points.txt
homematicip-2.4.0.dist-info/top_level.txt
homematicip-2.4.0.dist-info/RECORD
