Metadata-Version: 2.4
Name: homematicip
Version: 2.4.0
Summary: An API for the homematicip cloud
Author-email: Thomas Hahn <homematicip-rest-api@outlook.com>
License: GPL-3.0-or-later
Project-URL: Homepage, https://github.com/hahn-th/homematicip-rest-api
Project-URL: Repository, https://github.com/hahn-th/homematicip-rest-api.git
Project-URL: Issues, https://github.com/hahn-th/homematicip-rest-api/issues
Project-URL: Changelog, https://github.com/hahn-th/homematicip-rest-api/blob/master/CHANGELOG.md
Keywords: homematicip cloud,homematicip
Classifier: Programming Language :: Python :: 3
Classifier: Programming Language :: Python :: 3.12
Requires-Python: >=3.12
License-File: LICENSE.txt
Requires-Dist: requests>=2.32.0
Requires-Dist: websockets>=13.1
Requires-Dist: aiohttp>=3.10.11
Requires-Dist: httpx>=0.27.2
Dynamic: license-file
